writecoder/prompt.py
writecoder/work.py
writecoder/writecoder.py
writecoder-0.1.1.dist-info/METADATA
writecoder-0.1.1.dist-info/WHEEL
writecoder-0.1.1.dist-info/top_level.txt
writecoder-0.1.1.dist-info/RECORD
