Metadata-Version: 2.4
Name: writecoder
Version: 0.1.1
Summary: Add your description here
Requires-Python: >=3.10
Requires-Dist: llmada>=0.1.8
